htsimaging/__init__.py
htsimaging/bleach_chase/__init__.py
htsimaging/bleach_chase/stat.py
htsimaging/endocytosis/__init__.py
htsimaging/endocytosis/io.py
htsimaging/endocytosis/vid.py
htsimaging/endocytosis/viz.py
htsimaging/lib/__init__.py
htsimaging/lib/io.py
htsimaging/lib/stat.py
htsimaging/lib/utils.py
htsimaging/segment/__init__.py
htsimaging/segment/region.py
htsimaging/spt/__init__.py
htsimaging/spt/io.py
htsimaging/spt/stat.py
htsimaging/spt/viz.py
htsimaging/viz/__init__.py
htsimaging/viz/colors.py
htsimaging/viz/image.py
htsimaging/viz/stat.py
htsimaging-1.0.5.dist-info/LICENCE.txt
htsimaging-1.0.5.dist-info/METADATA
htsimaging-1.0.5.dist-info/WHEEL
htsimaging-1.0.5.dist-info/top_level.txt
htsimaging-1.0.5.dist-info/RECORD
