Metadata-Version: 2.1
Name: htsimaging
Version: 1.0.5
Summary: High-Throughput Single-cell Imaging analysis.
Home-page: http://github.com/rraadd88/htsimaging
Author: rraadd88
Author-email: rohanadandage@gmail.com
License: General Public License v. 3
Classifier: Programming Language :: Python
Classifier: Programming Language :: Python :: 3
Classifier: Programming Language :: Python :: 3.7
Classifier: Programming Language :: Python :: 3.8
Classifier: Programming Language :: Python :: 3.9
Classifier: License :: OSI Approved :: MIT License
Classifier: Operating System :: OS Independent
Requires-Python: >=3.7, <4
License-File: LICENCE.txt
Requires-Dist: roux >=0.0.9
Requires-Dist: scikit-image
Requires-Dist: argh
Requires-Dist: seaborn
Requires-Dist: fastparquet
Provides-Extra: all
Requires-Dist: numba ; extra == 'all'
Requires-Dist: trackpy ; extra == 'all'
Requires-Dist: pims ==0.4.1 ; extra == 'all'
Provides-Extra: dev
Requires-Dist: pytest ; extra == 'dev'
Requires-Dist: jupyter ; extra == 'dev'
Requires-Dist: ipywidgets ; extra == 'dev'
Requires-Dist: ipykernel ; extra == 'dev'
Requires-Dist: black ; extra == 'dev'
Requires-Dist: coveralls ==3.* ; extra == 'dev'
Requires-Dist: flake8 ; extra == 'dev'
Requires-Dist: isort ; extra == 'dev'
Requires-Dist: pytest-cov ==2.* ; extra == 'dev'
Requires-Dist: testbook ; extra == 'dev'
Requires-Dist: papermill ; extra == 'dev'
Requires-Dist: lazydocs ; extra == 'dev'
Requires-Dist: regex ; extra == 'dev'
Provides-Extra: spt
Requires-Dist: pims ==0.4.1 ; extra == 'spt'
Requires-Dist: trackpy ; extra == 'spt'
Requires-Dist: numba ; extra == 'spt'
